vms.py
vms-0.1.dist-info/DESCRIPTION.rst
vms-0.1.dist-info/METADATA
vms-0.1.dist-info/RECORD
vms-0.1.dist-info/WHEEL
vms-0.1.dist-info/entry_points.txt
vms-0.1.dist-info/metadata.json
vms-0.1.dist-info/top_level.txt
